twutil/__init__.py
twutil/collect.py
twutil/data.py
twutil/preprocess.py
twutil/twutil.py
twutil-0.2.2.dist-info/DESCRIPTION.rst
twutil-0.2.2.dist-info/METADATA
twutil-0.2.2.dist-info/metadata.json
twutil-0.2.2.dist-info/RECORD
twutil-0.2.2.dist-info/top_level.txt
twutil-0.2.2.dist-info/WHEEL
