Metadata-Version: 2.0
Name: twutil
Version: 0.2.2
Summary: Utilities for manipulating tweets
Home-page: https://github.com/tapilab/twutil
Author: Aron Culotta
Author-email: aronwc@gmail.com
License: BSD
Keywords: twutil
Platform: UNKNOWN
Classifier: Development Status :: 2 - Pre-Alpha
Classifier: Intended Audience :: Developers
Classifier: License :: OSI Approved :: BSD License
Classifier: Natural Language :: English
Classifier: Programming Language :: Python :: 2
Classifier: Programming Language :: Python :: 2.6
Classifier: Programming Language :: Python :: 2.7
Classifier: Programming Language :: Python :: 3
Classifier: Programming Language :: Python :: 3.3
Requires-Dist: TwitterAPI
Requires-Dist: wheel
